usk/Sensor.py
usk/__init__.py
usk/utills.py
usk-0.1.12.dist-info/LICENSE
usk-0.1.12.dist-info/METADATA
usk-0.1.12.dist-info/WHEEL
usk-0.1.12.dist-info/top_level.txt
usk-0.1.12.dist-info/RECORD
