Metadata-Version: 2.1
Name: usk
Version: 0.1.12
Summary: UniSat Software Kit
Home-page: https://github.com/unisatkz/USK
Author: Yaakov Azat
Author-email: a@azat.ai
License: MIT License
Requires-Dist: setuptools
Requires-Dist: pigpio
Requires-Dist: bme680
Requires-Dist: smbus
Requires-Dist: adafruit-circuitpython-bno055
Requires-Dist: SI1145
